wiktionary_translate/__init__.py
wiktionary_translate/example.py
wiktionary_translate/wiktionary_translate.py
wiktionary_translate-0.1.1.dist-info/LICENSE
wiktionary_translate-0.1.1.dist-info/METADATA
wiktionary_translate-0.1.1.dist-info/WHEEL
wiktionary_translate-0.1.1.dist-info/top_level.txt
wiktionary_translate-0.1.1.dist-info/RECORD
