Metadata-Version: 2.1
Name: wiktionary-translate
Version: 0.1.1
Summary: Get English translations of foreign word with Wiktionary
Home-page: https://github.com/Persie0/wiktionary_translate
Author: Marvin Perzi
Author-email: hashcod3@protonmail.com
License: mpl-2.0
Keywords: wiktionary,dictionary
Classifier: Development Status :: 5 - Production/Stable
Classifier: Intended Audience :: Developers
Classifier: Topic :: Software Development :: Build Tools
Classifier: License :: OSI Approved :: Mozilla Public License 2.0 (MPL 2.0)
Classifier: Programming Language :: Python :: 3
Classifier: Programming Language :: Python :: 3.9
Classifier: Programming Language :: Python :: 3.10
Requires-Python: >=3.6
License-File: LICENSE
